lime/__init__.py
lime/billingmodels.cpython-310-x86_64-linux-gnu.so
lime/campaigns.cpython-310-x86_64-linux-gnu.so
lime/config.cpython-310-x86_64-linux-gnu.so
lime/customers.cpython-310-x86_64-linux-gnu.so
lime/data_formatter.cpython-310-x86_64-linux-gnu.so
lime/fetcher.cpython-310-x86_64-linux-gnu.so
lime/gateways.cpython-310-x86_64-linux-gnu.so
lime/lime_base.cpython-310-x86_64-linux-gnu.so
lime/membership.cpython-310-x86_64-linux-gnu.so
lime/offers.cpython-310-x86_64-linux-gnu.so
lime/orders.cpython-310-x86_64-linux-gnu.so
lime/payments.cpython-310-x86_64-linux-gnu.so
lime/products.cpython-310-x86_64-linux-gnu.so
lime/prospects.cpython-310-x86_64-linux-gnu.so
lime/transaction.cpython-310-x86_64-linux-gnu.so
lime/batch_submitter/__init__.py
lime/batch_submitter/batch_base.cpython-310-x86_64-linux-gnu.so
lime/batch_submitter/batch_updater.cpython-310-x86_64-linux-gnu.so
lime/batch_submitter/order_canceller.cpython-310-x86_64-linux-gnu.so
lime/batch_submitter/order_submitter.cpython-310-x86_64-linux-gnu.so
lime_orderswrkpi-3.3.0.dist-info/METADATA
lime_orderswrkpi-3.3.0.dist-info/WHEEL
lime_orderswrkpi-3.3.0.dist-info/top_level.txt
lime_orderswrkpi-3.3.0.dist-info/RECORD
