Metadata-Version: 2.4
Name: lime-orderswrkpi
Version: 3.3.0
Author: Kenny
Requires-Python: >=3.10
Requires-Dist: requests
Requires-Dist: pandas==1.5.3
Requires-Dist: cython
Requires-Dist: ftfy
Requires-Dist: keyrings.google.artifactregistry-auth
Requires-Dist: cryptography<=42.0.8
